README.md
setup.py
netmanager/__init__.py
netmanager/firebasertdb.py
netmanager/netrequest.py
netmanager.egg-info/PKG-INFO
netmanager.egg-info/SOURCES.txt
netmanager.egg-info/dependency_links.txt
netmanager.egg-info/top_level.txt