Metadata-Version: 2.1
Name: netmanager
Version: 2.1
Summary: Author: Danila Kisluk
Home-page: UNKNOWN
Author-email: dankis12a@gmail.com
License: UNKNOWN
Platform: UNKNOWN
